waldur_ansible/__init__.py
waldur_ansible/common/__init__.py
waldur_ansible/common/apps.py
waldur_ansible/common/backend.py
waldur_ansible/common/cache_utils.py
waldur_ansible/common/exceptions.py
waldur_ansible/common/extension.py
waldur_ansible/common/filters.py
waldur_ansible/common/managers.py
waldur_ansible/common/models.py
waldur_ansible/common/serializers.py
waldur_ansible/common/urls.py
waldur_ansible/common/utils.py
waldur_ansible/common/views.py
waldur_ansible/playbook_jobs/__init__.py
waldur_ansible/playbook_jobs/admin.py
waldur_ansible/playbook_jobs/apps.py
waldur_ansible/playbook_jobs/backend.py
waldur_ansible/playbook_jobs/executors.py
waldur_ansible/playbook_jobs/extension.py
waldur_ansible/playbook_jobs/filters.py
waldur_ansible/playbook_jobs/handlers.py
waldur_ansible/playbook_jobs/models.py
waldur_ansible/playbook_jobs/serializers.py
waldur_ansible/playbook_jobs/tasks.py
waldur_ansible/playbook_jobs/urls.py
waldur_ansible/playbook_jobs/views.py
waldur_ansible/playbook_jobs/migrations/0001_initial.py
waldur_ansible/playbook_jobs/migrations/0002_add_parameter_order.py
waldur_ansible/playbook_jobs/migrations/0003_playbook_image.py
waldur_ansible/playbook_jobs/migrations/0004_add_spl_key_subnet_user.py
waldur_ansible/playbook_jobs/migrations/0005_add_job_deleting_status.py
waldur_ansible/playbook_jobs/migrations/0006_immutable_default_json.py
waldur_ansible/playbook_jobs/migrations/__init__.py
waldur_auth_bcc/__init__.py
waldur_auth_bcc/apps.py
waldur_auth_bcc/client.py
waldur_auth_bcc/extension.py
waldur_auth_bcc/serializers.py
waldur_auth_bcc/urls.py
waldur_auth_bcc/views.py
waldur_auth_saml2/__init__.py
waldur_auth_saml2/admin.py
waldur_auth_saml2/apps.py
waldur_auth_saml2/auth.py
waldur_auth_saml2/extension.py
waldur_auth_saml2/filters.py
waldur_auth_saml2/handlers.py
waldur_auth_saml2/log.py
waldur_auth_saml2/models.py
waldur_auth_saml2/serializers.py
waldur_auth_saml2/tasks.py
waldur_auth_saml2/urls.py
waldur_auth_saml2/utils.py
waldur_mastermind-4.5.1.dist-info/LICENSE.md
waldur_mastermind-4.5.1.dist-info/METADATA
waldur_mastermind-4.5.1.dist-info/WHEEL
waldur_mastermind-4.5.1.dist-info/entry_points.txt
waldur_mastermind-4.5.1.dist-info/top_level.txt
waldur_mastermind-4.5.1.dist-info/RECORD
